snek5000_cbox/Snakefile
snek5000_cbox/__init__.py
snek5000_cbox/_version.py
snek5000_cbox/cbox.usr.f
snek5000_cbox/output.py
snek5000_cbox/solver.py
snek5000_cbox/templates/SIZE_cbox.j2
snek5000_cbox/templates/__init__.py
snek5000_cbox/toolbox/CHKPOINTD
snek5000_cbox/toolbox/CHKPTMSTPD
snek5000_cbox/toolbox/FRAMELP
snek5000_cbox/toolbox/IOTOOLD
snek5000_cbox/toolbox/MAP2D
snek5000_cbox/toolbox/MNTRLOGD
snek5000_cbox/toolbox/MNTRTMRD
snek5000_cbox/toolbox/README.md
snek5000_cbox/toolbox/RPRMD
snek5000_cbox/toolbox/SFDD
snek5000_cbox/toolbox/STATD
snek5000_cbox/toolbox/__init__.py
snek5000_cbox/toolbox/chkpoint.f
snek5000_cbox/toolbox/chkpt_mstp.f
snek5000_cbox/toolbox/frame.f
snek5000_cbox/toolbox/io_tools.f
snek5000_cbox/toolbox/io_tools_block.f
snek5000_cbox/toolbox/map2D.f
snek5000_cbox/toolbox/math_tools.f
snek5000_cbox/toolbox/mntrlog.f
snek5000_cbox/toolbox/mntrlog_block.f
snek5000_cbox/toolbox/mntrtmr.f
snek5000_cbox/toolbox/mntrtmr_block.f
snek5000_cbox/toolbox/rprm.f
snek5000_cbox/toolbox/rprm_block.f
snek5000_cbox/toolbox/sfd.f
snek5000_cbox/toolbox/stat.f
snek5000_cbox/toolbox/stat_IO.f
snek5000_cbox/toolbox/stat_extras_dummy.f
snek5000_cbox-0.2.0.dist-info/LICENSE
snek5000_cbox-0.2.0.dist-info/METADATA
snek5000_cbox-0.2.0.dist-info/WHEEL
snek5000_cbox-0.2.0.dist-info/entry_points.txt
snek5000_cbox-0.2.0.dist-info/top_level.txt
snek5000_cbox-0.2.0.dist-info/RECORD
