Metadata-Version: 2.1
Name: snek5000-cbox
Version: 0.2.0
Summary: Snek5000 solver for the cbox (convective box) case
License: BSD-3-Clause
License-File: LICENSE
Requires-Dist: snek5000 (>=0.9.0rc3)
Provides-Extra: tests
Requires-Dist: nox ; extra == 'tests'
Requires-Dist: pytest ; extra == 'tests'
Requires-Dist: coverage[toml] ; extra == 'tests'
Requires-Dist: pytest-cov ; extra == 'tests'
Requires-Dist: pytest-datadir ; extra == 'tests'
Requires-Dist: pytest-mock ; extra == 'tests'
Requires-Dist: ipython ; extra == 'tests'
Requires-Dist: scipy ; extra == 'tests'
